sysmon/__init__.py
sysmon/alerts.py
sysmon/cli.py
sysmon/config.py
sysmon/core.py
sysmon/display.py
sysmon/models.py
sysmon/storage.py
sysmon/utils.py
sysmonitor-0.1.1.dist-info/licenses/LICENSE
sysmonitor-0.1.1.dist-info/METADATA
sysmonitor-0.1.1.dist-info/WHEEL
sysmonitor-0.1.1.dist-info/entry_points.txt
sysmonitor-0.1.1.dist-info/top_level.txt
sysmonitor-0.1.1.dist-info/RECORD
