Metadata-Version: 2.4
Name: sysmonitor
Version: 0.1.1
Summary: A beautiful terminal-based system monitoring tool
Author-email: Numair Khan <ornor6@gmail.com>
License: MIT
Project-URL: Homepage, https://github.com/OR-6/sysmon
Project-URL: Documentation, https://github.com/OR-6/sysmon#readme
Project-URL: Repository, https://github.com/OR-6/sysmon
Project-URL: Issues, https://github.com/OR-6/sysmon/issues
Keywords: system,monitoring,dashboard,cli,terminal
Classifier: Development Status :: 4 - Beta
Classifier: Intended Audience :: Developers
Classifier: Intended Audience :: System Administrators
Classifier: License :: OSI Approved :: MIT License
Classifier: Programming Language :: Python :: 3
Classifier: Programming Language :: Python :: 3.8
Classifier: Programming Language :: Python :: 3.9
Classifier: Programming Language :: Python :: 3.10
Classifier: Programming Language :: Python :: 3.11
Classifier: Programming Language :: Python :: 3.12
Classifier: Programming Language :: Python :: 3.13
Requires-Python: >=3.8
License-File: LICENSE
Requires-Dist: psutil>=5.9.0
Requires-Dist: click>=8.0.0
Requires-Dist: rich>=13.0.0
Requires-Dist: pyyaml>=6.0
Requires-Dist: pydantic>=2.0.0
Provides-Extra: dev
Requires-Dist: pytest>=7.0.0; extra == "dev"
Requires-Dist: black>=22.0.0; extra == "dev"
Requires-Dist: flake8>=4.0.0; extra == "dev"
Requires-Dist: mypy>=0.950; extra == "dev"
Dynamic: license-file
